Metadata-Version: 2.1
Name: neural-chat
Version: 0.0.5
Summary: Simple interface for neural chatbots.
Author: Verve
Author-email: <verve_is_god@protonmail.com>
Keywords: python,neural,machine learning,chatbots,chat,artificial intelligence,virtual assistant,voice
Classifier: Development Status :: 4 - Beta
Classifier: Intended Audience :: Developers
Classifier: Programming Language :: Python :: 3
Classifier: Operating System :: Unix
Classifier: Operating System :: Microsoft :: Windows
License-File: License.txt
